setup.py
BMI_Calculator/__init__.py
BMI_Calculator/bmi_calculate.py
TestBMI_Calculator.egg-info/PKG-INFO
TestBMI_Calculator.egg-info/SOURCES.txt
TestBMI_Calculator.egg-info/dependency_links.txt
TestBMI_Calculator.egg-info/not-zip-safe
TestBMI_Calculator.egg-info/top_level.txt