Metadata-Version: 1.0
Name: TestBMI-Calculator
Version: 0.1.0
Summary: Just test to create puckage
Home-page: UNKNOWN
Author: Kakada Sam
Author-email: UNKNOWN
License: UNKNOWN
Platform: UNKNOWN
